<?xml version="1.0" encoding="UTF-8"?>
<patent-document ucid="EP-2959442-A1" country="EP" doc-number="2959442" kind="A1" date="20151230" family-id="49713083" file-reference-id="317925" date-produced="20180825" status="corrected" lang="DE"><bibliographic-data><publication-reference fvid="160453219" ucid="EP-2959442-A1"><document-id><country>EP</country><doc-number>2959442</doc-number><kind>A1</kind><date>20151230</date><lang>DE</lang></document-id></publication-reference><application-reference ucid="EP-13799547-A" is-representative="NO"><document-id mxw-id="PAPP193869406" load-source="docdb" format="epo"><country>EP</country><doc-number>13799547</doc-number><kind>A</kind><date>20131204</date><lang>DE</lang></document-id><document-id mxw-id="PAPP193869407" load-source="patent-office" format="original"><country>EP</country><doc-number>13799547.8</doc-number><date>20131204</date><lang>DE</lang></document-id></application-reference><priority-claims><priority-claim mxw-id="PPC162034209" ucid="DE-102012112967-A" load-source="docdb"><document-id format="epo"><country>DE</country><doc-number>102012112967</doc-number><kind>A</kind><date>20121221</date></document-id></priority-claim><priority-claim mxw-id="PPC162031758" ucid="EP-2013075461-W" linkage-type="W" load-source="docdb"><document-id format="epo"><country>EP</country><doc-number>2013075461</doc-number><kind>W</kind><date>20131204</date></document-id></priority-claim></priority-claims><technical-data><classifications-ipcr><classification-ipcr mxw-id="PCL-1988519967" load-source="docdb">G06Q  20/42        20120101ALI20140709BHEP        </classification-ipcr><classification-ipcr mxw-id="PCL-1988525059" load-source="docdb">G06Q  20/32        20120101ALI20140709BHEP        </classification-ipcr><classification-ipcr mxw-id="PCL-1988526814" load-source="docdb">G06Q  20/20        20120101AFI20140709BHEP        </classification-ipcr><classification-ipcr mxw-id="PCL-1988527380" load-source="docdb">G06Q  20/38        20120101ALI20140709BHEP        </classification-ipcr><classification-ipcr mxw-id="PCL-1988527549" load-source="docdb">G06F  21/42        20130101ALI20140709BHEP        </classification-ipcr></classifications-ipcr><classifications-cpc><classification-cpc mxw-id="PCL-1608515902" load-source="docdb" scheme="CPC">G06Q  20/425       20130101 LI20180808BHEP        </classification-cpc><classification-cpc mxw-id="PCL-1608515903" load-source="docdb" scheme="CPC">G06Q  20/385       20130101 LI20180808BHEP        </classification-cpc><classification-cpc mxw-id="PCL-1608515904" load-source="docdb" scheme="CPC">G06Q  20/3278      20130101 LI20180808BHEP        </classification-cpc><classification-cpc mxw-id="PCL-1608515905" load-source="docdb" scheme="CPC">G06Q  20/3276      20130101 LI20180808BHEP        </classification-cpc><classification-cpc mxw-id="PCL-1608515906" load-source="docdb" scheme="CPC">G06Q  20/327       20130101 LI20180808BHEP        </classification-cpc><classification-cpc mxw-id="PCL-1608515907" load-source="docdb" scheme="CPC">G06Q  20/32        20130101 LI20180808BHEP        </classification-cpc><classification-cpc mxw-id="PCL-1608515908" load-source="docdb" scheme="CPC">G06Q  20/20        20130101 LI20180808BHEP        </classification-cpc><classification-cpc mxw-id="PCL-1608515909" load-source="docdb" scheme="CPC">G06F  21/42        20130101 LI20180808BHEP        </classification-cpc><classification-cpc mxw-id="PCL-1987765425" load-source="docdb" scheme="CPC">G06Q  20/347       20130101 FI20151205BHEP        </classification-cpc><classification-cpc mxw-id="PCL-1987772922" load-source="docdb" scheme="CPC">G06Q  20/40        20130101 LI20151205BHEP        </classification-cpc></classifications-cpc><invention-title mxw-id="PT165551123" lang="DE" load-source="patent-office">ONLINE TRANSAKTIONSSYSTEM</invention-title><invention-title mxw-id="PT165551124" lang="EN" load-source="patent-office">ONLINE TRANSACTION SYSTEM</invention-title><invention-title mxw-id="PT165551125" lang="FR" load-source="patent-office">SYSTÈME DE TRANSACTIONS EN LIGNE</invention-title></technical-data><parties><applicants><applicant mxw-id="PPAR1103334224" load-source="docdb" sequence="1" format="epo"><addressbook><last-name>SQWIN SA</last-name><address><country>CH</country></address></addressbook></applicant><applicant mxw-id="PPAR1103330187" load-source="docdb" sequence="1" format="intermediate"><addressbook><last-name>SQWIN SA</last-name></addressbook></applicant><applicant mxw-id="PPAR1101640866" load-source="patent-office" sequence="1" format="original"><addressbook><last-name>Sqwin SA</last-name><iid>101465226</iid><address><street>Route de la Gare 36</street><city>2012 Auvernier</city><country>CH</country></address></addressbook></applicant></applicants><inventors><inventor mxw-id="PPAR1103322302" load-source="docdb" sequence="1" format="epo"><addressbook><last-name>GULCHENKO VICTOR</last-name><address><country>RU</country></address></addressbook></inventor><inventor mxw-id="PPAR1103331102" load-source="docdb" sequence="1" format="intermediate"><addressbook><last-name>GULCHENKO, VICTOR</last-name></addressbook></inventor><inventor mxw-id="PPAR1101652857" load-source="patent-office" sequence="1" format="original"><addressbook><last-name>GULCHENKO, VICTOR</last-name><address><street>Oeder Weg 110</street><city>60318 Frankfurt</city><country>RU</country></address></addressbook></inventor></inventors><agents><agent mxw-id="PPAR1101647585" load-source="patent-office" sequence="1" format="original"><addressbook><last-name>2K Patentanwälte Blasberg Kewitz &amp; Reichel</last-name><iid>100061307</iid><address><street>Partnerschaft mbB Schumannstrasse 27</street><city>60325 Frankfurt am Main</city><country>DE</country></address></addressbook></agent></agents></parties><international-convention-data><pct-or-regional-filing-data ucid="EP-2013075461-W"><document-id><country>EP</country><doc-number>2013075461</doc-number><kind>W</kind><date>20131204</date><lang>DE</lang></document-id></pct-or-regional-filing-data><pct-or-regional-publishing-data ucid="WO-2014095362-A1"><document-id><country>WO</country><doc-number>2014095362</doc-number><kind>A1</kind><date>20140626</date><lang>DE</lang></document-id></pct-or-regional-publishing-data><designated-states><ep-contracting-states><country mxw-id="DS660792158" load-source="docdb">AL</country><country mxw-id="DS660713136" load-source="docdb">AT</country><country mxw-id="DS660792160" load-source="docdb">BE</country><country mxw-id="DS660633847" load-source="docdb">BG</country><country mxw-id="DS660742285" load-source="docdb">CH</country><country mxw-id="DS660637049" load-source="docdb">CY</country><country mxw-id="DS660713137" load-source="docdb">CZ</country><country mxw-id="DS660792161" load-source="docdb">DE</country><country mxw-id="DS660637050" load-source="docdb">DK</country><country mxw-id="DS660637059" load-source="docdb">EE</country><country mxw-id="DS660716899" load-source="docdb">ES</country><country mxw-id="DS660633848" load-source="docdb">FI</country><country mxw-id="DS660633849" load-source="docdb">FR</country><country mxw-id="DS660792162" load-source="docdb">GB</country><country mxw-id="DS660637060" load-source="docdb">GR</country><country mxw-id="DS660792163" load-source="docdb">HR</country><country mxw-id="DS660713138" load-source="docdb">HU</country><country mxw-id="DS660742286" load-source="docdb">IE</country><country mxw-id="DS660792164" load-source="docdb">IS</country><country mxw-id="DS660633850" load-source="docdb">IT</country><country mxw-id="DS660637061" load-source="docdb">LI</country><country mxw-id="DS660635082" load-source="docdb">LT</country><country mxw-id="DS660713143" load-source="docdb">LU</country><country mxw-id="DS660635091" load-source="docdb">LV</country><country mxw-id="DS660635092" load-source="docdb">MC</country><country mxw-id="DS660722917" load-source="docdb">MK</country><country mxw-id="DS660722918" load-source="docdb">MT</country><country mxw-id="DS660713144" load-source="docdb">NL</country><country mxw-id="DS660716900" load-source="docdb">NO</country><country mxw-id="DS660742295" load-source="docdb">PL</country><country mxw-id="DS660635094" load-source="docdb">PT</country><country mxw-id="DS660713145" load-source="docdb">RO</country><country mxw-id="DS660635103" load-source="docdb">RS</country><country mxw-id="DS660742296" load-source="docdb">SE</country><country mxw-id="DS660635104" load-source="docdb">SI</country><country mxw-id="DS660716901" load-source="docdb">SK</country><country mxw-id="DS660742297" load-source="docdb">SM</country><country mxw-id="DS660722923" load-source="docdb">TR</country></ep-contracting-states><ep-extended-states><ep-extended-state-data><country>BA</country></ep-extended-state-data><ep-extended-state-data><country>ME</country></ep-extended-state-data></ep-extended-states></designated-states></international-convention-data><office-specific-data><eptags><ep-no-a-document-published>*</ep-no-a-document-published></eptags></office-specific-data></bibliographic-data><abstract mxw-id="PA134851568" ref-ucid="WO-2014095362-A1" lang="DE" load-source="patent-office"><p num="0000">Verfahren zur Durchführung einer digitalen Transaktion über ein mobiles Endgerät, mit einem Kassensystem, das mit einem drahtlosen lokalen Netzwerk verbunden ist, umfassend die Schritte: - Erzeugen eines einmaligen digitalen Codes durch das Kassensystem, das zum Einleiten der Transaktion dient; - automatisches Freischalten eines Netzzugangs zum lokalen drahtlosen Netzwerk nach dem Erzeugen des einmaligen digitalen Codes, wobei der Zugriff auf das drahtlose Netzwerk durch den digitalen Code erlaubt wird; - Verbinden des mobilen Endgerätes mit dem lokalen Netzwerk mit Hilfe des digitale Codes und Bereitstellen von Informationen des Endgerätes an das Kassensystem, - Nach dem Erhalten der Informationen von dem Endgerät durch das Kassensystem erfolgt eine Freigabe der Transaktion durch das Kassensystem.</p></abstract><abstract mxw-id="PA135206553" ref-ucid="WO-2014095362-A1" lang="DE" source="national office" load-source="docdb"><p>Verfahren zur Durchführung einer digitalen Transaktion über ein mobiles Endgerät, mit einem Kassensystem, das mit einem drahtlosen lokalen Netzwerk verbunden ist, umfassend die Schritte: - Erzeugen eines einmaligen digitalen Codes durch das Kassensystem, das zum Einleiten der Transaktion dient; - automatisches Freischalten eines Netzzugangs zum lokalen drahtlosen Netzwerk nach dem Erzeugen des einmaligen digitalen Codes, wobei der Zugriff auf das drahtlose Netzwerk durch den digitalen Code erlaubt wird; - Verbinden des mobilen Endgerätes mit dem lokalen Netzwerk mit Hilfe des digitale Codes und Bereitstellen von Informationen des Endgerätes an das Kassensystem, - Nach dem Erhalten der Informationen von dem Endgerät durch das Kassensystem erfolgt eine Freigabe der Transaktion durch das Kassensystem.</p></abstract><abstract mxw-id="PA134851569" ref-ucid="WO-2014095362-A1" lang="EN" load-source="patent-office"><p num="0000">Method for performing a digital transaction using a mobile terminal, having a cash system that is connected to a wireless local area network, comprising the following steps: - production of a unique digital code by the cash system that is used for initiating the transaction; - automatic enabling of network access to the wireless local area network after production of the unique digital code, with access to the wireless network being permitted by the digital code; - connection of the mobile terminal to the local area network using the digital code and provision of information from the terminal for the cash system; - after the information has been obtained by the cash system from the terminal, the cash system provides clearance for the transaction.</p></abstract><abstract mxw-id="PA135206554" ref-ucid="WO-2014095362-A1" lang="EN" source="national office" load-source="docdb"><p>Method for performing a digital transaction using a mobile terminal, having a cash system that is connected to a wireless local area network, comprising the following steps: - production of a unique digital code by the cash system that is used for initiating the transaction; - automatic enabling of network access to the wireless local area network after production of the unique digital code, with access to the wireless network being permitted by the digital code; - connection of the mobile terminal to the local area network using the digital code and provision of information from the terminal for the cash system; - after the information has been obtained by the cash system from the terminal, the cash system provides clearance for the transaction.</p></abstract><abstract mxw-id="PA134851570" ref-ucid="WO-2014095362-A1" lang="FR" load-source="patent-office"><p num="0000">L'invention concerne un procédé permettant de réaliser par le biais d'un terminal mobile une transaction numérique avec un système de caisse relié à un réseau local sans fil, comprenant les étapes suivantes : - génération par le système de caisse d'un code numérique unique servant à engager la transaction; - activation automatique d'un accès au réseau local sans fil après la génération du code numérique unique, l'accès au réseau sans fil étant autorisé par le code numérique; - connexion du terminal mobile au réseau local à l'aide du code numérique et transmission d'informations du terminal au système de caisse, - après obtention des informations du terminal par le système de caisse, validation de la transaction par le système de caisse.</p></abstract><abstract mxw-id="PA135206555" ref-ucid="WO-2014095362-A1" lang="FR" source="national office" load-source="docdb"><p>L'invention concerne un procédé permettant de réaliser par le biais d'un terminal mobile une transaction numérique avec un système de caisse relié à un réseau local sans fil, comprenant les étapes suivantes : - génération par le système de caisse d'un code numérique unique servant à engager la transaction; - activation automatique d'un accès au réseau local sans fil après la génération du code numérique unique, l'accès au réseau sans fil étant autorisé par le code numérique; - connexion du terminal mobile au réseau local à l'aide du code numérique et transmission d'informations du terminal au système de caisse, - après obtention des informations du terminal par le système de caisse, validation de la transaction par le système de caisse.</p></abstract><description mxw-id="PDES69851954" ref-ucid="WO-2014095362-A1" lang="DE" load-source="patent-office"><!-- EPO <DP n="3"/>--><p id="p0001" num="0001">Die Erfindung betrifft ein online Transaktionssystem Gebiet der Erfindung: </p><p id="p0002" num="0002"> Ein Finanztransaktionssystem ist ein computergestütztes Anwendungssystem, mit der überwiegend bargeldlose Transaktionen durchgeführt werden. I.d.R. basieren diese Systeme auf Datenbanksystemen, mit denen Transaktionen ausgeführt werden. Für die ordnungsgemäße Ausführung einer Transaktion bestehen Schutzmaßnahmen, die gewährleisten, dass eine Datenbank stets einen korrekten Zustand aufweist. Im mobilen payment bzw. Zahlungsverkehr ist es wichtig die Identität des Zahlenden festzustellen und einen Missbrauch zu vermeiden.</p><p id="p0003" num="0003">Die WO 2008 / 050132 A2 zeigt ein Verfahren, bei dem die Transaktionsdaten parallel durch ein mobiles Endgerät und ein Kassensystem übertragen werden und nur dann zur Ausführung kommen, wenn beide Daten identisch sind. </p><p id="p0004" num="0004">Die WO 2010/129357 A2 offenbart ein Verfahren zur Bereitstellung einer dynamischen Karten-Verifikation von mobilen Endgeräten. </p><p id="p0005" num="0005">Übersicht über die Erfindung: </p><p id="p0006" num="0006">Grundsatz der vorliegenden Erfindung ist die Auseinanderziehung der Informationsfluten vom Käufer und Verkäufer im Moment des Einkaufs. Jede Partei sendet an das Zahlungssystem ihr 
<!-- EPO <DP n="4"/>-->
Informationspaket über ihren Verbindungskanal. So werden bei jedem Einkauf zwei unabhängige Informationspakete an das </p><p id="p0007" num="0007">Zahlungssystem geschickt. </p><p id="p0008" num="0008"> Dabei enthält jedes Informationspaket ein Pflichtelement - eine einmalige Nummer des Kassenbelegs. Nur dank dieses Elements kann das Zahlungssystem bzw. das Banksystem zwei Informationspakete finden und sie miteinander verbinden. </p><p id="p0009" num="0009"> Dieser Ansatz kann sowohl im realen, mit Kassensystemen, als auch im Internethandel erfolgen. </p><p id="p0010" num="0010">Die Erfindung umfasst ein Verfahren zur Durchführung einer digitalen Transaktion über ein mobiles Endgerät, mit einem </p><p id="p0011" num="0011">Kassensystem. Das Verfahren umfasst hierbei die Schritte: </p><p id="p0012" num="0012"> - Erzeugen eines einmaligen digitalen Codes durch das </p><p id="p0013" num="0013">Kassensystem, der die Transaktion identifiziert, </p><p id="p0014" num="0014"> - Übermitteln der Transaktionsdaten mit dem einmaligen digitalen Code an eine Bank des Besitzers des Endgerätes über ein ersten digitalen Netzwerkpfad; </p><p id="p0015" num="0015"> - paralleles Übermitteln des digitalen Codes und der </p><p id="p0016" num="0016">Kontoinformationen an die Bank, ausgelöst durch das mobile </p><p id="p0017" num="0017">Endgerät, über einen zweiten digitalen Netzwerkpfad; </p><p id="p0018" num="0018"> - Zusammenführen der Transaktionsdaten vom Kassensystem und der Kontoinformationen durch die Bank, die durch das mobile Endgerät ausgelöst wurden, und Freigabe der Transaktion bei erfolgreicher Zusammenführung. Eine Zusammenführung ist immer dann erfolgreich, wenn die Codes übereinstimmen. Hierdurch wird über </p><p id="p0019" num="0019">unterschiedliche Pfade, die bei der Bank zusammengeführt werden, einer Bank die Zustimmung für die Transaktion mitgeteilt. </p><p id="p0020" num="0020">Damit die Bank die Kontodaten kennt, werden die Kontodaten z.B. in einem Internet-Dienst abgelegt, wie einem Email-Account oder einem Account in einem sozialen Netzwerk, und das mobile Endgerät kann durch Anmeldung bei diesem Internet-Dienst eine Übermittlung der Kontodaten und des digitalen Codes auslösen. Der Code kann dabei manuell oder automatisch in das Gerät eingegeben werden, wie weiter unten ausgeführt wird. 
<!-- EPO <DP n="5"/>-->
Die einmalige Kennung kann weiterhin, über ein Pattern Password, (Mustersperre) , das auf dem Kassengerät oder auf dem Kassenbeleg abgebildet ist, eingegeben werden. Auch die Stimmeingabe ist denkbar. Die automatische Übertragung durch NFC während der </p><p id="p0021" num="0021">Verbindung mit dem Kassengerät wird weiter unten beschrieben. </p><p id="p0022" num="0022">In einer weiteren Ausführungsform kann der einmalige digitale Code, nur einmalig verwendet werden, um sich mit einem lokalen drahtlosen Netzwerk des Kassensystems zu verbinden, wobei </p><p id="p0023" num="0023">aufgrund der Verbindung eine IMSI, IMEI oder MAC-Adresse des mobilen Endgerätes erlangt wird, die in die Transaktionsdaten einfließt, wobei parallel das mobile Endgerät die IMSI, IMEI oder MAC-Adresse an die Bank übermittelt, und eine Transaktion nur freigegeben wird, wenn auch die IMSI, IMEI oder MAC-Adressen übereinstimmen. Hierdurch wird nicht nur der Code sondern auch die Adresse des Endgerätes überprüft. In einer alternativen </p><p id="p0024" num="0024">Ausführungsform ist die IMSI, IMEI oder MAC-Adresse der Code selber . </p><p id="p0025" num="0025">In der bevorzugten Ausführungsform wird der digitale Code auf eine Quittung vom Kassensystem ausgedruckt, um diesen dann manuell im mobilen Gerät einzutippen. Alternativ kann der Code auch über ein Netzwerk an das mobile Endgerät übergeben werden. Dabei wird der einmalige digitale Code über eine drahtlose </p><p id="p0026" num="0026">Verbindung vom Kassensystem and das mobile Endgerät übertragen, vorzugsweise per NFC oder Bluetooth oder WIFI, so dass das mobile Endgerät die Daten ohne manuelles Eintippen weiterleiten kann. </p><p id="p0027" num="0027">Das Netzwerk des Kassensystems identifiziert das mobile Endgerät im Moment seines Anschlusses an dem Netzwerk durch eine IMSI - Nummer (International Mobile Subscriber, </p><p id="p0028" num="0028"> Identity) oder IMEI (International Mobile Equipment Identity) , oder MAC (Media Access Control Address) und leitet die Daten an das Kassensystem weiter. 
<!-- EPO <DP n="6"/>-->
Zusätzlich können durch eine Abfrage bei einem Telefonprovider die Standortkoordinaten des mobilen Endgerätes und die </p><p id="p0029" num="0029">tatsächliche geografische Lage des Kassensystems verglichen werden, und wenn die Koordinaten nicht übereinstimmen, so kann die Transaktion blockiert werden. Die Koordinaten können somit ein weiteres Vergleichskriterium sein, um die Daten sicher zusammenzuführen und die Transaktion auszulösen. </p><p id="p0030" num="0030">Nach einem erfolgreichen Abschluss der Transaktion wird der </p><p id="p0031" num="0031">Zugang zu dem lokalen Netzwerk auf der Basis des Codes </p><p id="p0032" num="0032">automatisch abgeschaltet. Hierbei ist das drahtlose lokale </p><p id="p0033" num="0033">Netzwerk ein WIFI. </p><p id="p0034" num="0034">In einer weiteren Ausführungsform umfasst die Erfindung ein </p><p id="p0035" num="0035">System, umfassend ein mobiles Endgerät, ein Kassensystem und ein Banksystem, das durch eine Einrichtung gekennzeichnet ist, die das Verfahren nach einem oder mehreren der vorhergehenden </p><p id="p0036" num="0036">Ansprüche implementiert. </p><p id="p0037" num="0037">Weiterhin im Bereich des Internet betrifft die Erfindung ein Verfahren zur Durchführung einer digitalen Transaktion über ein mobiles Endgerät, mit einem Kassensystem, das mit einem </p><p id="p0038" num="0038">drahtlosen lokalen Netzwerk verbunden ist, umfassend die </p><p id="p0039" num="0039">Schritte : </p><p id="p0040" num="0040"> - Erzeugen eines einmaligen digitalen Codes durch das </p><p id="p0041" num="0041">Kassensystem, das zum Einleiten der Transaktion dient; </p><p id="p0042" num="0042"> - automatisches Freischalten eines Netzzugangs zum lokalen drahtlosen Netzwerk nach dem Erzeugen des einmaligen digitalen Codes, wobei der Zugriff auf das drahtlose Netzwerk durch den digitalen Code erlaubt wird; </p><p id="p0043" num="0043"> - Verbinden des mobilen Endgerätes mit dem lokalen Netzwerk mit Hilfe des digitalen Codes und Bereitstellen von Informationen des Endgerätes an das Kassensystem, </p><p id="p0044" num="0044"> - Nach dem Erhalten der Informationen von dem Endgerät durch das Kassensystem erfolgt eine Freigabe der Transaktion durch das Kassensystem. 
<!-- EPO <DP n="7"/>-->
Bei dem drahtlosen Netzwerk handele es sich vorzugsweise um ein WLAN Netzwerk, das im lokalen Kassenbereich ausgebildet ist. </p><p id="p0045" num="0045"> In einer bevorzugten Ausführungsform verwaltet das Kassensystem über ein Benutzerkonto die Zuordnung der Identität des mobilen Endgerätes zu einem Kundenkonto, indem die Bank-Informationen wie Kreditkarteninformationen oder Kontonummer, Bankleitzahl etc. abgelegt sind. Durch die Zuordnung der Mac-Adresse zu diesen Transaktionsinformationen wird erreicht, dass der Besitzer des mobilen Gerätes keinerlei weitere Kontodaten übermitteln muss. Anhand der Mac Adresse erfolgt eine Zuordnung zu den Kontodaten und eine Freigabe kann erfolgen. Um einen Betrug zu vermeiden, sind bei den Kundendaten ebenfalls die Daten des mobilen </p><p id="p0046" num="0046">Providers hinterlegt, so dass der Mobile Provider überprüfen kann, ob sich das Gerät tatsächlich örtlich in dem Bereich der Kasse bewegt und kein Diebstahl der Mac-Adresse vorliegt. Neben der Mac-Adresse können auch andere Kennzeichnungen des mobilen Endgerätes verwendet werden, wie sie weiter unten beschrieben werden. Alternativ überträgt das mobile Endgerät Kontodaten durch eine Anwendung auf dem mobilen Endgerät an eine Zieladresse im mobilen Netzwerk. Anhand der eindeutigen Kennung und der </p><p id="p0047" num="0047">Kontodaten kann erneut vom Provider des mobilen Netzwerkes des mobilen Endgerätes der Standort des mobilen Endgerätes überprüft werden und eine Freigabe kann von Seiten des mobilen Providers erfolgen. Es ist zu beachten, dass ebenfalls eine Abbuchung vom Konto des mobilen Providers erfolgen kann, so dass eine </p><p id="p0048" num="0048">Rechnungsstellung über die Telefonrechnung erfolgen kann. </p><p id="p0049" num="0049">In der bevorzugten Ausführungsform ist der einmalige digitale Code nur einmalig zu verwenden, um sich mit dem lokalen </p><p id="p0050" num="0050">drahtlosen Netzwerk zu verbinden. Es handelt sich somit um einen Einmalcode, der nach einer einmaligen Benutzung keinerlei Zugang erlaubt . </p><p id="p0051" num="0051">Der einmalige Code kann eine beliebige Anzahl von Ziffern oder Buchstaben enthalten. Der Kunde darf aber bei einer manuellen Eingabe nur die letzten vier Ziffern eingeben. 
<!-- EPO <DP n="8"/>-->
Das System kann einen ziemlich langen Code (damit beim vielen Einkäufen keine Wiederholungen auftreten) generieren, wählt aber dabei entweder die ersten oder die letzten vier Symbole als einen einmaligen Code für das Netzwerkbetreten aus. </p><p id="p0052" num="0052"> Sobald der verkürzte Code eingegeben ist, leitet das System dem Smartphone den kompletten (langen) Originalcode weiter. </p><p id="p0053" num="0053">Der einmalige Code kann in unterschiedlicher Form übermittelt werden. Der digitale Code kann auf einer Quittung vom </p><p id="p0054" num="0054">Kassensystem ausgedruckt werden, um diesen dann manuell in ein mobiles Gerät einzutippen. In einer alternativen Ausführungsform wird diese auch als Barcode erzeugt, der dann von einer Anwendung des mobilen Endgerätes eingelesen werden kann. Dieser Barcode kann in der Regel über die Kamera des mobilen Endgerätes </p><p id="p0055" num="0055">detektiert werden. In einer alternativen Ausführungsform kann die Quittung auch über eine mobile Funkschnittstelle per Bluetooth, NFC oder als SMS an das mobile Endgerät übermittelt werden. Wenn auf dem mobilen Endgerät eine spezielle Anwendung installiert ist, kann dieser Code gleich interpretiert werden und zur </p><p id="p0056" num="0056">Autorisierung im mobilen Netzwerk genutzt werden. Vorzugsweise muss der Benutzer noch die Eingabe bestätigen, bevor ein Zugang zum mobilen Netzwerk bzw. drahtlosen Netzwerk freigeschaltet wird . </p><p id="p0057" num="0057">Im ersten Informationsfluss erfolgt eine Codeeingabe für den Netzzugang. Dadurch ist der Kunde im Netz; das Netzwerk kann jetzt die MAC-Adresse des Kunden zuordnen, und der Kunde wird danach vom Netz getrennt. Daraufhin schickt das Kassensystem ein Informationspaket (enthält MAC-Adresse des Käufers, den </p><p id="p0058" num="0058">Zahlungsbetrag und den Kassenbeleg, eigene Verkäuferangaben) an das Zahlungssystem (z.B. Bank oder VISA usw.) weiter. </p><p id="p0059" num="0059">Parallel dazu im zweiten Informationsfluss sendet das </p><p id="p0060" num="0060">Smartphone den Kassenbeleg an den Anwendungsanbieter/Soziale Netzwerk (z.B. Facebook oder Googlemail) . Die Anwendung fügt die Bankdaten des Käufers dem Informationspaket zu und sendet dieses 
<!-- EPO <DP n="9"/>-->
an das Zahlungssystem (z.B. Bank oder VISA usw.) . Das </p><p id="p0061" num="0061">Zahlungssystem vergleicht beide Informationspakete. Der Verkäufer bekommt eine Zusage vom Zahlungssystem. Die Kundenbank bekommt eine Zusage vom Zahlungssystem. </p><p id="p0062" num="0062">Bei einer der nichtmanuellen Codeeingabe ist eine automatische Eingabe durch die NFC - Technologie möglich. </p><p id="p0063" num="0063">Um den Zugang zum lokalen mobilen/drahtlosen Netzwerk zu </p><p id="p0064" num="0064">erreichen, ist das Kassensystem mit einem Steuerungssystem für das mobile Netzwerk verbunden, um den digitalen Code austauschen. So kann zum Beispiel das Steuerungssystem über das RADIUS </p><p id="p0065" num="0065">Protokoll die Zugangspunkte für das kabellose Netzwerk steuern. Sollte sich ein Benutzer am kabellosen Netzwerk anmelden, so können entsprechende Anfragen beim Steuerungssystem vom </p><p id="p0066" num="0066">Zugangspunkt des kabellosen Netzwerkes gestellt werden. Andere Technologien sind natürlich denkbar. Grundsätzlich sollte jedoch ein Standard verwendet werden um die kabellosen Zugangspunkte zu steuern, so dass das Einmal-Passwort effektiv genutzt wird. </p><p id="p0067" num="0067">Nachdem eine Anmeldung erfolgt ist und die notwendigen Daten ausgetauscht wurden setzt das Steuerungssystem sofort den Zugang zurück . </p><p id="p0068" num="0068">In einer möglichen Ausführungsform, wie oben beschrieben, läuft eine Anwendung auf dem mobilen Endgerät, über die der digitale Code eingegeben wird und eine Anmeldung am mobilen Netzwerk erfolgt, und wobei nach der Anmeldung Kontoinformationen, </p><p id="p0069" num="0069">Kreditkarteninformationen oder IMSI-Informationen an das mobile Netzwerk von der Anwendung übermittelt werden, um eine </p><p id="p0070" num="0070">Transaktion abzuschließen. Um die Informationen an die richtige Stelle im Netzwerk zu übermitteln, wird bei der Anmeldung des mobilen Endgerätes eine Adresse übermittelt, (zum Beispiel über das DHCP-Protokoll) an die die relevanten Identifikationsdaten des mobilen Endgerätes zu übertragen sind. Hierdurch ist es ebenfalls möglich Kontoinformationen und weitere Details zu übertragen. Mit der Anmeldung am mobilen Netzwerk wird eine 
<!-- EPO <DP n="10"/>-->
Netzwerkadresse dem mobilen Endgerät mitgeteilt, an die die </p><p id="p0071" num="0071">Kontoinformationen, Kreditkarteninformationen oder IMSI- Informationen zu übermitteln sind. Nachdem diese Informationen erlangt wurden, erfolgt eine Übermittlung dieser Informationen in der Regel nur auf Basis einer Zustimmung. Weiterhin können </p><p id="p0072" num="0072">Zertifikate und ähnliche Details abgefragt werden, um </p><p id="p0073" num="0073">sicherzustellen, dass nur vertrauenswürdige Instanzen diese </p><p id="p0074" num="0074">Informationen enthalten. </p><p id="p0075" num="0075">In einer alternativen Ausführungsform spricht das Steuersystem für das mobile Netzwerk das mobile Endgerät nach der Anmeldung über das Netzwerk an, um Informationen für die Durchführung einer digitalen Transaktion vom mobilen Endgerät zu erlangen. Wobei das Steuersystem des Netzwerks das mobile Endgerät im Moment seines Anschlusses (durch eine IMSI - Nummer (International Mobile Subscriber, Identity) oder IMEI</p><p id="p0076" num="0076">(International Mobile Equipment Identity), oder MAC (Media Access Control address) identifiziert und die Daten an das Kassensystem weiterleitet. </p><p id="p0077" num="0077">Sollte ein Kundenkonto beim Unternehmen vorhanden sein, greift das Kassensystem anhand der Netzwerkidentifizierung auf eine Datenbank zu, in der die Kontoinformationen und/oder ein </p><p id="p0078" num="0078">Netzwerkprovider in Relation zu der Netzwerkidentifizierung abgelegt sind. </p><p id="p0079" num="0079"> Durch die Transaktionsdaten und/oder die Kennung vom Kassensystem können die Zugangsdaten wie oben beschrieben wurde durch einen Telefonprovider über ein Telefonnetzwerk an das mobile Endgerät übermittelt werden, wobei der Telefonprovider die Korrektheit der Identifizierung überprüft.</p><p id="p0080" num="0080">Hierbei überprüft der Telefonprovider die IMSI, IMEI oder MAC. Vorzugsweise überprüft der Telefonprovider die</p><p id="p0081" num="0081">Standortkoordinaten des mobilen Endgerätes und die tatsächliche geografische Lage des Kassensystems, indem er diese vergleicht, und wenn die Koordinaten nicht übereinstimmen, so kann die 
<!-- EPO <DP n="11"/>-->
Transaktion blockiert werden bzw. eine entsprechende Warnmeldung an das Kassensystem gesendet werden. </p><p id="p0082" num="0082">Sollte sich herausstellen, dass sowohl die Transaktions-Daten als auch die Standortkoordinaten korrekt sind, so werden die Transaktionsdaten an eine entsprechende Clearingstelle übermittelt (eine Bank) , die die Transaktion letztendlich auf den Banksystemen durchführt. </p><p id="p0083" num="0083">Nach einem erfolgreichen Abschluss der Transaktion wird der Zugang zu dem lokalen Netzwerk auf der Basis des Codes </p><p id="p0084" num="0084">automatisch abgeschaltet. </p><p id="p0085" num="0085">Figuren Beschreibung: </p><p id="p0086" num="0086">Figur 1 zeigt schematisch den Ablauf des Verfahrens ohne WLAN;</p><p id="p0087" num="0087">Figur 2 zeigt schematisch den Ablauf des Verfahrens mit WLAN;</p><p id="p0088" num="0088">Figur 3 zeigt schematisch den Ablauf des Verfahrens mit WLAN und</p><p id="p0089" num="0089">MAC Adresse; </p><p id="p0090" num="0090"> Figur 4 zeigt schematisch den Ablauf des Verfahrens, wobei die Kennung nicht manuell, sondern per NFC-Netz auf das mobile </p><p id="p0091" num="0091">Endegerät eingegeben wird. </p><p id="p0092" num="0092">Beschreibung einer Ausführungsform: </p><p id="p0093" num="0093">Grundlage der Idee ist die Auseinanderziehung der </p><p id="p0094" num="0094">Informationsflüsse vom Käufer und Verkäufer im Moment des </p><p id="p0095" num="0095">Einkaufs. Jede Partei schickt an das Zahlungssystem ihr </p><p id="p0096" num="0096">Informationspaket über ihren Verbindungskanal. So werden bei jedem Einkauf zwei unabhängige Informationspakete an das </p><p id="p0097" num="0097">Zahlungssystem geschickt. </p><p id="p0098" num="0098">Dabei enthält jedes Informationspaket ein Pflichtelement - eine einmalige Nummer des Kassenbelegs. Nur dank diesem Element kann das Zahlungssystem zwei Informationspakete finden und sie zusammen verbinden. 
<!-- EPO <DP n="12"/>-->
Figur 1 zeigt schematisch den Ablauf eines Verfahrens bei dem kein WLAN eingesetzt wird und eine Zahlung im Internet erfolgt. </p><p id="p0099" num="0099">Grundelement ist, dass der Käufer Nutzer eines sozialen </p><p id="p0100" num="0100">Netzwerkes/Messenger ist, indem er seine Zahlungsdaten angegeben hat. Hierüber erfolgt eine vereinzelte Informationsversendung über die Zahlung vom Käufer und Verkäufer. Es wird dabei eine einmalige Kassenbelegnummer als Verbindungsmöglichkeit verwendet. </p><p id="p0101" num="0101">Gemäß Figur 1, wird in Schritt 1A Folgendes durchgeführt. </p><p id="p0102" num="0102"> Der Online-Händler generiert eine einmalige Kassenbelegnummer und sendet sie an das Zahlungssystem (samt Zahlungsbetrag und eigene Bankverbindung) (1A) . </p><p id="p0103" num="0103">Parallel dazu meldet sich der Käufer bei seinem sozialen Netzwerk an oder ist bereits angemeldet (1B) . </p><p id="p0104" num="0104"> Der Käufer sendet seine Kassenbelegnummer an das soziale Netzwerk (lc) . Das soziale Netzwerk sendet diese Kassenbelegnummer mit den persönlichen Käuferdaten an das Zahlungssystem weiter (2B) . Das Zahlungssystem bekommt zwei Informationspakete mit der gleichen Kassenbelegnummer und verbindet sie für die Bearbeitung (2A) . Das Zahlungssystem prüft dann beim Bank Emittent der Karte die </p><p id="p0105" num="0105">Zahlungsfähigkeit des Kunden (3) und bekommt ggfs. eine </p><p id="p0106" num="0106">Anfragebestätigung (4). Das Zahlungssystem sendet dann eine </p><p id="p0107" num="0107">Anfragebestätigung (5) an die Acquiring Bank, die dann wieder an das Kaufhaus (6) bzw. das Kassensystem weitergeleitet wird die die Information für die Zahlung freigeben. </p><p id="p0108" num="0108">In Figur 2 sind die Grundelemente, dass der Käufer ein Nutzer eines sozialen Netzwerkes/Messenger ist, wo er seine </p><p id="p0109" num="0109">Zahlungsdaten angegeben hat. Es erfolgt eine vereinzelte </p><p id="p0110" num="0110">Informationsversendung über die Zahlung vom Käufer und Verkäufer. Es erfolgt eine Verwendung der einmaligen Kassenbelegnummer als Verbindungsmöglichkeit zwischen zwei Informationspaketen. So erfolgt eine Verwendung der MAC-Adresse des WLAN-Netzwerkes des Verkäufers (Kaufhaus, Cafe, Parkhaus usw.) für die </p><p id="p0111" num="0111">Verbindungsmöglichkeit zwischen zwei Informationspaketen. Die 
<!-- EPO <DP n="13"/>-->
Handlungsreihenfolge ist grundsätzlich ähnlich wie bei der Figur</p><p id="p0112" num="0112">1, jedes Informationspaket enthält aber hier eine MAC-Adresse des WLAN-Netzwerkes des Verkäufers. </p><p id="p0113" num="0113"> Neben der Kassenbelegnummer dient die MAC-Adresse für die </p><p id="p0114" num="0114">Zusammenführung der Informationen seitens des Zahlungssystems bei einem Einkauf. Der Käufer sucht sich das WLAN-Netzwerk des </p><p id="p0115" num="0115">Verkäufers in seinem Smartphone aus und meldet sich mit einem Passwort (einmalige Kassenbelegnummer) an. </p><p id="p0116" num="0116">Das Smartphone bekommt Informationen über die MAC-Adresse des WLAN-Netzes des Verkäufers, die an das Zahlungssystem </p><p id="p0117" num="0117">mitgeschickt wird. </p><p id="p0118" num="0118">Das WLAN-Netzwerk des Verkäufers erhält ein Signal über den </p><p id="p0119" num="0119">Einkaufswunsch und sendet die Daten an das Zahlungssystem (1) . Die weiteren Schritte entsprechen Figur 1 wobei zusätzlich noch die MAC-Adresse des WLAN-Netzwerkes verglichen wird. </p><p id="p0120" num="0120">Die Figur 3 zeigt wiederum eine abgewandelte Version. Die </p><p id="p0121" num="0121">Grundelemente sind wiederum, dass der Käufer Nutzer eines </p><p id="p0122" num="0122">sozialen Netzwerkes/Messenger ist, wo er seine Zahlungsdaten angegeben hat. Es erfolgt eine vereinzelte, aufgespaltene </p><p id="p0123" num="0123">Informationsversendung über die Zahlung vom Käufer und Verkäufer. Die Verwendung der einmaligen Kassenbelegnummer als </p><p id="p0124" num="0124">Verbindungsmöglichkeit zwischen zwei Informationspaketen wird unter Verwendung der MAC-Adresse des WLAN-Netzwerkes des </p><p id="p0125" num="0125">Verkäufers (Kaufhaus, Cafe, Parkhaus usw.) und unter Verwendung der MAC-Adresse des Käufers zusammengeführt. Hierdurch werden 3 Parameter verglichen. </p><p id="p0126" num="0126">Die Handlungsreihenfolge ist dieselbe wie bei den Varianten 1 und</p><p id="p0127" num="0127">2, jedes Informationspaket enthält aber hier außerdem eine MAC- Adresse des Smartphones des Käufers. </p><p id="p0128" num="0128"> Neben der Kassenbelegnummer dient diese MAC-Adresse für die </p><p id="p0129" num="0129">Zusammenführung auf Seiten des Zahlungssystems. </p><p id="p0130" num="0130"> Der Käufer sucht das WLAN-Netzwerk des Verkäufers in seinem </p><p id="p0131" num="0131">Smartphone aus und meldet sich mit einem Passwort (einmalige Kassenbelegnummer) an. 
<!-- EPO <DP n="14"/>-->
Das WLAN-Netzwerk des Verkäufers erhält die MAC-Adresse des </p><p id="p0132" num="0132">Käufersmartphones und umgekehrt. Jede Partei sendet die MAC- Adresse ihres Kontrahenten zusammen mit dem kompletten </p><p id="p0133" num="0133">Informationspaket an das Zahlungssystem. (1) (2) (3) </p><p id="p0134" num="0134"> Beide MAC-Adressen sind in diesem Fall Zusatzkomponenten bei der Suche nach zwei an das Zahlungssystem verschickte </p><p id="p0135" num="0135">Informationspakete im Rahmen eines Einkaufs. </p><p id="p0136" num="0136">Die Figuren 2 und 3 zeigen schematisch den Ablauf des </p><p id="p0137" num="0137">vorliegenden Verfahrens. In einem ersten Schritt erzeugt ein Kassensystem einen Kassenzettel für eine Transaktion mit einem einmaligen Zugangskennwort für das lokale drahtlose Netzwerk. Das Kassensystem gibt diese Nummer weiter an ein </p><p id="p0138" num="0138">Zugangssteuerungssystem, das für den Zugang zu dem mobilen lokalen Netzwerk zuständig ist. Nachdem sich das mobile Endgerät angemeldet hat, erlangt das Kassensystem die entsprechende </p><p id="p0139" num="0139">Information über die Anmeldung vom Zugangssystem (das nicht dargestellt ist) . Das Kassensystem fragt dann bei der Hausbank des Kaufhauses an, ob mit der Kennung des mobilen Endgerätes ein Konto verknüpft ist, auf dem die entsprechenden Bankdaten des Kunden abgelegt sind. Die Acquiring Bank gibt diese dann an ein Zahlungssystem (VISA, Mastercard) weiter, das vom Sozialen </p><p id="p0140" num="0140">Netzwerk ebenfalls Informationen erlangt. Sollte ggfs. auch noch die Identifikation des mobilen Endgerätes mit dem Standort übereinstimmen, was beim Telefonprovider abgefragt wurde, so gibt es noch zusätzliche Daten. Sollte der Telefonanbieter/Provider feststellen, dass Standort und Kennung des mobilen Gerätes übereinstimmen und kein Missbrauch vorliegt, so wird eine </p><p id="p0141" num="0141">Rückmeldung an das Zahlungssystem gegeben. Das Serversystem teilt dies der Hausbank wiederum mit, so dass sichergestellt ist, dass kein Missbrauch vorliegt. Nachdem diese Details ausgetauscht wurden, übernimmt das Zahlungssystem den Abschluss der </p><p id="p0142" num="0142">Transaktion über den Bank Emittent. Nachdem diese erfolgte, wird dann eine Überweisung an das Kaufhaus übermittelt. Das </p><p id="p0143" num="0143">Kassensystem wird ebenfalls über den erfolgreichen Abschluss der Transaktion informiert. 
<!-- EPO <DP n="15"/>-->
Die Figur 4 zeigt zusätzlich, dass die einmalige Kennung über ein NFC-Netz an das Smartphone übermittelt wird. Dieses sendet die Daten dann an das soziale Netzwerk bzw. Netzwerkdienste, die dann die Daten wiederum an die Bank weiterleiten. Parallel werden die Daten auch vom Kaufhaus zur Bank übermittelt. </p><p id="p0144" num="0144">In einer möglichen Ausführungsform erfolgt das Verfahren wie folgt : </p><p id="p0145" num="0145"> Der Käufer wählt die Ware aus [oder ein Produkt, bzw. Leistung im Cafe] . Im Weiteren wird die Reihenfolge der Tätigkeiten beim Kauf der Ware und der Bezahlung der Ware oder der Leistungen (der Geldempfänger wird „Kaufhaus [Cafe]" genannt) beschrieben </p><p id="p0146" num="0146"> Die Kasse/Kassensystem im Kaufhaus [Cafe] ist mit dem drahtlosen lokalen Netzwerk des Kaufhauses [Cafes] unmittelbar oder </p><p id="p0147" num="0147">mittelbar verbunden. Zumindest besteht eine Verbindung zu einem Steuersystem, das den Zugang zum mobilen Netzwerk verwaltet. Das Steuersystem kann z.B. über Regeleinheiten und Standardprotokolle den Zugriff für die Authentifizierung vorgeben. </p><p id="p0148" num="0148">Der Mitarbeiter des Kaufhauses [Cafes] scannt die ausgewählte Ware ein, eine Quittungsnummer mit einem Endbetrag des Einkaufs wird vom Kassengerät/ Kassensystem (der Verkäufer kann durch einen Computer ersetzt werden) erzeugt. Die Nummer ist </p><p id="p0149" num="0149">vorzugsweise eine Zufallszahl, die durch einen Generator erzeugt wird . </p><p id="p0150" num="0150">Beim Kauf und während der Bezahlung wird eine einmalige </p><p id="p0151" num="0151">Quittungs-, bzw. Belegnummer generiert. Die Zahl der Ziffer </p><p id="p0152" num="0152">(Zahlenreihe) kann beliebig sein. </p><p id="p0153" num="0153">Mit dem Generieren des Kassenbelegs wird für das WLAN des </p><p id="p0154" num="0154">Kaufhauses [Cafes] ein einmaliges Kennwort /Zutritts Code für den Netzzutritt erzeugt: a) Entweder mit einer Zahlenreihe, die genau mit der </p><p id="p0155" num="0155">Kassenzettelnummer übereinstimmt b) Oder mit einer komplett anderen Nummer, die aber mit der </p><p id="p0156" num="0156">Kassenzettelnummer „verbunden" ist, so dass der Benutzer dieses erkennt . 
<!-- EPO <DP n="16"/>-->
Hierbei kann es sich um einen N-stelligen Code als Kennwort handeln. Dieser ist komfortabel und kundenfreundlich und für die Wahrnehmung und schnelle Eingabe geeignet. </p><p id="p0157" num="0157"> Dieses einmalige Kennwort ist ausschließlich für einen einzigen Netzzutritt von einem Außengerät gültig. </p><p id="p0158" num="0158">Der Kunde sieht auf seinem Smartphone eine Liste der möglichen drahtlosen Netzwerke, wählt das im Moment benötigte Netz und aktiviert dieses über den Code. Das WLAN des Cafes oder </p><p id="p0159" num="0159">Kaufhauses fordert ein Kennwort für eine Freischaltung. </p><p id="p0160" num="0160">Der Kunde gibt als Code die N-Nummer seines Kassenbelegs ein. Die Wi-Fi-Nutzung vom Kunden und die Eingabe der Kassenbelegnummer</p><p id="p0161" num="0161">(gleichzeitig eines Kennwortes) bestätigt den Kundenwunsch einen bestimmten Betrag von seinem Konto abzubuchen. Das Konto kann hierbei ein lokales Konto beim Verkäufer sein, auf dem die eindeutige Kennung des mobilen Telefons und die Bankinformationen abgelegt sind. Alternativ kann anhand der Netzwerkkennung auch der Mobil-Funk-Provider festgestellt werden und eine Abbuchung über die Telefonrechnung erfolgen. In einer weiteren </p><p id="p0162" num="0162">Ausführungsform überträgt das mobile Endgerät Bank-Information</p><p id="p0163" num="0163">(Kredit-Karte, EC-Karte etc.) </p><p id="p0164" num="0164">Der kurzzeitige Anschluss zum WLAN eines Cafes oder Kaufhauses an sich gibt dem Kunden grundsätzlich keine weiteren Netzoptionen (wie z. B. die Möglichkeit eines InternetZugangs ) außer einer Wunschbestätigung einen bestimmten Betrag (auf dem Kassenzettel) zu bezahlen. </p><p id="p0165" num="0165">Das WLAN eines Cafes oder Kaufhauses initialisiert das Smartphone im Moment seines Anschlusses (durch eine IMSI - Nummer </p><p id="p0166" num="0166">(International Mobile Subscriber Identity) oder IMEI </p><p id="p0167" num="0167">(International Mobile Equipment Identity), oder MAC (Media Access</p><p id="p0168" num="0168">Control Address) ) und leitet die Daten an das Zahlungssystem weiter . </p><p id="p0169" num="0169">Die Daten können über den Kassenbeleg durch einen Telefonprovider übermittelt werden (der Telefonprovider erkennt in dem Fall die individuellen Merkmale des Kunden über sein Smartphone) 
<!-- EPO <DP n="17"/>-->
Anmerkung: Der Telefonanbieter kann für den Kunden als einen zusätzlichen Sicherheitsfilter dienen - die tatsächliche MAC- Adresse wird ergänzend überprüft (im Falle, wenn diese Adresse missbraucht wurde) . </p><p id="p0170" num="0170"> Wenn der Telefonanbieter eine Anfrage über eine </p><p id="p0171" num="0171">Kundenpersonifizierung durch sein Smartphone vom Cafe oder </p><p id="p0172" num="0172">Kaufhaus empfängt, kann er die GPS- Koordinaten des Smartphones und der tatsächlichen geografischen Lage des Kaufhauses oder Cafes vergleichen. Wenn die Koordinaten nicht übereinstimmen kann die Transaktion blockiert werden. </p><p id="p0173" num="0173">Noch eine Überprüfungsvariante wäre - der Telefonprovider kann den Aufenthaltsort des Smartphone durch seine IMSI/IMEI - Nummer sicherstellen. Dieser Aufenthaltsort muss dann mit der </p><p id="p0174" num="0174">tatsächlichen geografischen Lage des Cafes oder Kaufhauses verglichen werden. </p><p id="p0175" num="0175">Das Zahlungssystem leitet seine Anfrage an den Emittenten weiter (an die Bank, die eine Kredit-, bzw. EC-Karte dem Kunden </p><p id="p0176" num="0176">ausgegeben oder das Kundenkonto eröffnet hat) und empfängt eine Zu-oder absage, abhängig von der Zahlungsfähigkeit des Kunden. Dann wird das Kaufhaus/Cafe informiert, ob die Transaktion stattfinden darf. </p><p id="p0177" num="0177">Der Zugriff des Kundensmartphones zum WLAN des Kaufhauses oder Cafes wird nach einer erfolgreichen Bezahlung automatisch </p><p id="p0178" num="0178">abgeschaltet . </p><p id="p0179" num="0179">Zusätzliche ist Folgendes zu beachten: </p><p id="p0180" num="0180"> Andere Vermittler zwischen Zahlungssystem und Verkäufern sind möglich. Es kann zum Beispiel eine Sozialnetzanwendung sein, die im Kundensmartphone installiert ist. Diese Anwendung kann die Funktion übernehmen, die individuellen Kundencharakteristika an das Zahlungssystem weiterzuleiten. 
<!-- EPO <DP n="18"/>-->
Es ist auch eine andere Verbindung zwischen dem Verkäufer und der Kundenbank denkbar, so wie eine direkte Verbindung über den </p><p id="p0181" num="0181">Telefonanbieter - vorbei an dem traditionellen Zahlungssystem. 
</p></description><claims mxw-id="PCLM61332365" ref-ucid="WO-2014095362-A1" lang="DE" load-source="patent-office"><claim-statement><!-- EPO <DP n="19"/>-->Patentansprüche </claim-statement><claim id="clm-0001" num="1"><claim-text>1. Verfahren zur Durchführung einer digitalen Transaktion </claim-text><claim-text> über ein mobiles Endgerät, mit einem Kassensystem, </claim-text><claim-text> umfassend die Schritte: </claim-text><claim-text> - Erzeugen eines einmaligen digitalen Codes durch das Kassensystem, der die Transaktion identifiziert, </claim-text><claim-text> - Übermitteln der Transaktionsdaten mit dem einmaligen digitalen Code an eine Bank des Besitzers des Endgerätes über ein ersten digitalen Netzwerkpfad; </claim-text><claim-text> - paralleles Übermitteln des digitalen Codes und der </claim-text><claim-text> Kontoinformationen, ausgelöst durch das mobile Endgerät an die Bank, über einen zweiten digitalen Netzwerkpfad; </claim-text><claim-text> - Zusammenführen der Transaktionsdaten vom Kassensystem und der Kontoinformationen durch die Bank, die durch das mobile Endgerät ausgelöst wurden, und Freigabe der </claim-text><claim-text> Transaktion bei erfolgreicher Zusammenführung; dadurch gekennzeichnet, dass der einmalige digitale Code nur einmalig verwendet werden kann, um sich mit einem lokalen drahtlosen Netzwerk des Kassensystems zu verbinden, wobei aufgrund der Verbindung eine IMSI, IMEI oder MAC-Adresse des mobilen Endgerätes erlangt wird, die in die </claim-text><claim-text> Transaktionsdaten einfließt, wobei parallel das mobile Endgerät die IMSI, IMEI oder MAC-Adresse and die Bank übermittelt, und eine Transaktion nur freigegeben wird, wenn auch die IMSI, IMEI oder MAC-Adressen übereinstimmen. </claim-text></claim><claim id="clm-0002" num="2"><claim-text>2. Das Verfahren nach dem vorhergehenden Anspruch, wobei die Kontodaten in einem Internet-Dienst abgelegt sind, wie einem Email-Account oder einem Account in einem sozialen Netwerk, und das mobile Endgerät durch Anmeldung bei diesem Internet-Dienst eine Übermittlung der Kontodaten und des digitalen Codes auslöst. 
<!-- EPO <DP n="20"/>-->
</claim-text></claim><claim id="clm-0003" num="3"><claim-text>3. Das Verfahren nach einem oder mehreren der vorhergehenden Ansprüche, wobei der digitale Code auf eine Quittung vom Kassensystem ausgedruckt wird, um diesen dann manuell im mobilen Gerät einzutippen. </claim-text></claim><claim id="clm-0004" num="4"><claim-text>4. Das Verfahren nach einem oder mehreren der vorhergehenden Ansprüche, wobei das Netzwerk das mobile Endgerät im Moment seines Anschlusses (durch eine IMSI - Nummer (International Mobile Subscriber, </claim-text><claim-text> Identity) oder IMEI (International Mobile Equipment </claim-text><claim-text> Identity) , oder MAC (Media Access Control Address) ) identifiziert und die Daten an das Kassensystem </claim-text><claim-text> weiterleitet . </claim-text></claim><claim id="clm-0005" num="5"><claim-text>5. Das Verfahren nach einem der vier vorhergehenden </claim-text><claim-text> Ansprüche, wobei der Telefonprovider die </claim-text><claim-text> Standortkoordinaten des mobilen Endgerätes und die </claim-text><claim-text> tatsächliche geografische Lage des Kassensystems </claim-text><claim-text> vergleicht, und wenn die Koordinaten nicht übereinstimmen, so kann die Transaktion blockiert werden. </claim-text></claim><claim id="clm-0006" num="6"><claim-text>6. Das Verfahren nach einem oder mehreren der vorhergehenden Ansprüche, wobei nach einem erfolgreichen Abschluss der Transaktion der Zugang zu dem lokalen Netzwerk auf der Basis des Codes automatisch abgeschaltet wird. </claim-text></claim><claim id="clm-0007" num="7"><claim-text>7. Das Verfahren nach einem oder mehreren der vorhergehenden Ansprüche, wobei das drahtlose lokale Netzwerk ein WIFI ist . </claim-text></claim><claim id="clm-0008" num="8"><claim-text>8. Das Verfahren nach einem oder mehreren der vorhergehenden Ansprüche, wobei der einmalige digitale Code über eine drahtlose Verbindung vom Kassensystem and das mobile </claim-text><claim-text> Endgerät übertragen wird, vorzugsweise per NFC oder </claim-text><claim-text> Bluetooth oder WIFI, so dass das mobile Endgerät die Daten ohne manuelles Eintippen weiterleiten kann. 
<!-- EPO <DP n="21"/>-->
</claim-text></claim><claim id="clm-0009" num="9"><claim-text>9. System umfassend ein mobiles Endgerät, ein Kassensystem und ein Banksystem, gekennzeichnet durch eine Einrichtun die das Verfahren nach einem oder mehreren der </claim-text><claim-text> vorhergehenden Ansprüche implementiert. 
</claim-text></claim></claims><copyright>User acknowledges that Fairview Research LLC and its third party providers retain all right, title and interest in and to this xml under applicable copyright laws.  User acquires no ownership rights to this xml including but not limited to its format.  User hereby accepts the terms and conditions of the Licence Agreement</copyright></patent-document>
